CHANGES.rst
LICENSE
MANIFEST.in
README.rst
setup.cfg
setup.py
Flask_SignalBus.egg-info/PKG-INFO
Flask_SignalBus.egg-info/SOURCES.txt
Flask_SignalBus.egg-info/dependency_links.txt
Flask_SignalBus.egg-info/requires.txt
Flask_SignalBus.egg-info/top_level.txt
Flask_SignalBus.egg-info/zip-safe
docs/Makefile
docs/api.rst
docs/cli.rst
docs/conf.py
docs/index.rst
docs/make.bat
docs/rabbitmq.rst
docs/_templates/sidebarlogo.html
flask_signalbus/__init__.py
flask_signalbus/atomic.py
flask_signalbus/signalbus.py
flask_signalbus/signalbus_cli.py
flask_signalbus/utils.py
flask_signalbus/rabbitmq/__init__.py
flask_signalbus/rabbitmq/common.py
flask_signalbus/rabbitmq/consumer.py
flask_signalbus/rabbitmq/publisher.py
tests/conftest.py
tests/test_atomic.py
tests/test_rabbitmq.py
tests/test_signalbus.py
tests/test_signalbus_cli.py
tests/test_utils.py