Metadata-Version: 1.1
Name: Flask-SignalBus
Version: 0.5.18
Summary: A Flask-SQLAlchemy extension for atomically sending messages (signals) over a message bus
Home-page: https://github.com/epandurski/flask_signalbus
Author: Evgeni Pandurski
Author-email: epandurski@gmail.com
License: MIT
Platform: any
Classifier: Environment :: Web Environment
Classifier: Intended Audience :: Developers
Classifier: License :: OSI Approved :: BSD License
Classifier: Operating System :: OS Independent
Classifier: Topic :: Internet :: WWW/HTTP :: Dynamic Content
Classifier: Topic :: Software Development :: Libraries :: Python Modules
Classifier: Programming Language :: Python
Classifier: Programming Language :: Python :: 3
Classifier: Programming Language :: Python :: 3.4
Classifier: Programming Language :: Python :: 3.5
Classifier: Programming Language :: Python :: 3.6
Classifier: Programming Language :: Python :: 3.7
